sws_api_wrapper/Course.py
sws_api_wrapper/User.py
sws_api_wrapper/__init__.py
sws_api_wrapper/api.py
sws_api_wrapper-0.1.5.dist-info/METADATA
sws_api_wrapper-0.1.5.dist-info/WHEEL
sws_api_wrapper-0.1.5.dist-info/licenses/LICENSE.txt
sws_api_wrapper-0.1.5.dist-info/RECORD
