Metadata-Version: 2.1
Name: sws_api_wrapper
Version: 0.1.5
Summary: An API wrapper for So We Sign
Project-URL: Homepage, https://github.com/avivi55/SWS
Project-URL: Issues, https://github.com/avivi55/SWS/issues
Project-URL: Repository, https://github.com/avivi55/SWS.git
License: MIT License
License-File: LICENSE.txt
Keywords: so we sign,sowesign,sws
Classifier: License :: OSI Approved :: MIT License
Classifier: Programming Language :: Python :: 3
Requires-Python: >=3.8
Requires-Dist: user-agent
